edgeml/__init__.py
edgeml/pytorch/__init__.py
edgeml/pytorch/utils.py
edgeml/pytorch/graph/__init__.py
edgeml/pytorch/graph/bonsai.py
edgeml/pytorch/graph/protoNN.py
edgeml/pytorch/graph/rnn.py
edgeml/pytorch/trainer/__init__.py
edgeml/pytorch/trainer/bonsaiTrainer.py
edgeml/pytorch/trainer/fastTrainer.py
edgeml/pytorch/trainer/fastmodel.py
edgeml/pytorch/trainer/protoNNTrainer.py
edgeml/pytorch/trainer/srnnTrainer.py
edgeml/tf/__init__.py
edgeml/tf/utils.py
edgeml/tf/graph/__init__.py
edgeml/tf/graph/bonsai.py
edgeml/tf/graph/protoNN.py
edgeml/tf/graph/rnn.py
edgeml/tf/trainer/__init__.py
edgeml/tf/trainer/bonsaiTrainer.py
edgeml/tf/trainer/emirnnTrainer.py
edgeml/tf/trainer/fastTrainer.py
edgeml/tf/trainer/protoNNTrainer.py
edgeml-0.2.1.dist-info/METADATA
edgeml-0.2.1.dist-info/WHEEL
edgeml-0.2.1.dist-info/top_level.txt
edgeml-0.2.1.dist-info/RECORD
