Metadata-Version: 2.1
Name: edgeml
Version: 0.2.1
Summary: machine learning algorithms for edge devices developed at Microsoft Research India.
Home-page: https://github.com/Microsoft/EdgeML
Author: UNKNOWN
Author-email: UNKNOWN
License: MIT License
Platform: UNKNOWN
